phenodata/__init__.py
phenodata/command.py
phenodata/ftp.py
phenodata/util.py
phenodata/dwd/__init__.py
phenodata/dwd/cdc.py
phenodata/dwd/pheno.py
phenodata/dwd/presets.json
tests/__init__.py
tests/test_cli.py
tests/test_examples.py
tests/test_forecast.py
tests/test_metadata.py
tests/test_observations.py
tests/test_stations.py
tests/util.py
phenodata-0.13.1.dist-info/LICENSE
phenodata-0.13.1.dist-info/METADATA
phenodata-0.13.1.dist-info/WHEEL
phenodata-0.13.1.dist-info/entry_points.txt
phenodata-0.13.1.dist-info/top_level.txt
phenodata-0.13.1.dist-info/RECORD
