Metadata-Version: 2.1
Name: phenodata
Version: 0.13.1
Summary: phenodata is an acquisition and processing toolkit for open access phenology data
Home-page: https://github.com/earthobservations/phenodata
Author: Andreas Motl
Author-email: andreas.motl@panodata.org
License: AGPL 3, EUPL 1.2
Keywords: phenology phenology-data phenology-models phenology-modelling phenometrics opendata scientific research-data dwd gpm usa-npn
Classifier: Programming Language :: Python
Classifier: Programming Language :: Python :: 3
Classifier: Programming Language :: Python :: 3.7
Classifier: Programming Language :: Python :: 3.8
Classifier: Programming Language :: Python :: 3.9
Classifier: Programming Language :: Python :: 3.10
Classifier: Programming Language :: Python :: 3.11
Classifier: Development Status :: 4 - Beta
Classifier: Environment :: Console
Classifier: Environment :: Web Environment
Classifier: Intended Audience :: Developers
Classifier: Intended Audience :: Education
Classifier: Intended Audience :: End Users/Desktop
Classifier: Intended Audience :: Information Technology
Classifier: Intended Audience :: Science/Research
Classifier: License :: OSI Approved :: European Union Public Licence 1.2 (EUPL 1.2)
Classifier: License :: OSI Approved :: GNU Affero General Public License v3
Classifier: Natural Language :: English
Classifier: Natural Language :: German
Classifier: Natural Language :: Latin
Classifier: Operating System :: MacOS :: MacOS X
Classifier: Operating System :: POSIX :: Linux
Classifier: Topic :: Database
Classifier: Topic :: Education
Classifier: Topic :: Internet :: File Transfer Protocol (FTP)
Classifier: Topic :: Internet :: WWW/HTTP
Classifier: Topic :: Internet :: WWW/HTTP :: Indexing/Search
Classifier: Topic :: Scientific/Engineering
Classifier: Topic :: Scientific/Engineering :: Atmospheric Science
Classifier: Topic :: Scientific/Engineering :: Information Analysis
Classifier: Topic :: Scientific/Engineering :: Visualization
Classifier: Topic :: Software Development :: Libraries
Classifier: Topic :: System :: Archiving
Classifier: Topic :: Text Processing :: Filters
Classifier: Topic :: Text Processing :: Indexing
Classifier: Topic :: Utilities
License-File: LICENSE
Requires-Dist: arrow (<1.3,>=0.12.1)
Requires-Dist: attrs (>=17.4.0)
Requires-Dist: docopt (>=0.6.2)
Requires-Dist: dogpile.cache (<2,>=0.6.5)
Requires-Dist: pandas (<2.1,>=1.3)
Requires-Dist: platformdirs (<4)
Requires-Dist: requests (<3,>=2.18.4)
Requires-Dist: requests-ftp (<4,>=0.3.1)
Requires-Dist: tabulate (<0.10,>=0.8.2)
Requires-Dist: tqdm (<5,>=4.60)
Provides-Extra: sql
Requires-Dist: duckdb (<0.8,>=0.3) ; extra == 'sql'
Provides-Extra: test
Requires-Dist: datadiff (<3,>=2.0) ; extra == 'test'
Requires-Dist: marko (<2) ; extra == 'test'
Requires-Dist: proselint (==0.13.1) ; extra == 'test'
Requires-Dist: pytest (<8,>=6.1.0) ; extra == 'test'
Requires-Dist: pytest-cov (<5) ; extra == 'test'
Requires-Dist: pytest-doctest-ellipsis-markers ; extra == 'test'
